[
  {
    "suku_kata": ["Me", "ja", "ri", "lo"],
    "jawaban": "Meja"
  },
  {
    "suku_kata": ["Bu", "ku", "pa", "se"],
    "jawaban": "Buku"
  },
  {
    "suku_kata": ["Bo", "la", "pi", "du"],
    "jawaban": "Bola"
  },
  {
    "suku_kata": ["Ku", "da", "ni", "go"],
    "jawaban": "Kuda"
  },
  {
    "suku_kata": ["Sa", "pi", "le", "mu"],
    "jawaban": "Sapi"
  },
  {
    "suku_kata": ["Ru", "mah", "ka", "bo"],
    "jawaban": "Rumah"
  },
  {
    "suku_kata": ["Gu", "ru", "de", "fi"],
    "jawaban": "Guru"
  },
  {
    "suku_kata": ["Ma", "ta", "jo", "yu"],
    "jawaban": "Mata"
  },
  {
    "suku_kata": ["Ka", "ki", "ne", "po"],
    "jawaban": "Kaki"
  },
  {
    "suku_kata": ["Ba", "ju", "re", "ni"],
    "jawaban": "Baju"
  },
  {
    "suku_kata": ["To", "pi", "ga", "hu"],
    "jawaban": "Topi"
  },
  {
    "suku_kata": ["Su", "su", "ke", "ma"],
    "jawaban": "Susu"
  },
  {
    "suku_kata": ["Na", "si", "do", "la"],
    "jawaban": "Nasi"
  },
  {
    "suku_kata": ["Ay", "ah", "pe", "tu"],
    "jawaban": "Ayah"
  },
  {
    "suku_kata": ["I", "bu", "ra", "so"],
    "jawaban": "Ibu"
  }
  ]